{
  "version": 1,
  "source": "actv_telegram",
  "lastUpdated": "2026-05-02T18:37:22Z",
  "disruptions": [
    {
      "id": "tg-88a95504b1a8",
      "title": "Il traffico torna regolare",
      "description": "Il traffico torna regolare",
      "severity": "info",
      "lineAliases": [],
      "affectedStops": [],
      "lastUpdated": "2026-05-02T09:11:11Z",
      "startAt": "2026-05-02T09:11:11Z",
      "endAt": null,
      "source": "actv_telegram",
      "url": null
    },
    {
      "id": "tg-196adf3d8e45",
      "title": "#muoversivenezia ⚠️",
      "description": "#muoversivenezia ⚠️\n\nCausa incidente tra privati in via della libertà direzione Mestre all’altezza di Via Righi\n\n🚍 autobus deviati per San Giuliano e conseguenti forti ritardi in tutti gli orari di transito",
      "severity": "info",
      "lineAliases": [],
      "affectedStops": [],
      "lastUpdated": "2026-05-02T07:52:50Z",
      "startAt": "2026-05-02T07:52:50Z",
      "endAt": null,
      "source": "actv_telegram",
      "url": null
    },
    {
      "id": "tg-928675de0f59",
      "title": "Pronti per la prossima stagione in Lega Serie A",
      "description": "Pronti per la prossima stagione in Lega Serie A",
      "severity": "info",
      "lineAliases": [],
      "affectedStops": [],
      "lastUpdated": "2026-05-01T15:34:13Z",
      "startAt": "2026-05-01T15:34:13Z",
      "endAt": null,
      "source": "actv_telegram",
      "url": null
    },
    {
      "id": "tg-05757f503efe",
      "title": "🆕 AVM/Actv sarà presente al Venezia Comics per condividere la nuova campagna di comunicazione dedicata a chi ogni giorno",
      "description": "🆕 AVM/Actv sarà presente al Venezia Comics per condividere la nuova campagna di comunicazione dedicata a chi ogni giorno usa il trasporto pubblico, per viaggiare meglio, insieme. \n\nDall'1 al 3 maggio 2026, ci troverete all'ingresso del Forte Marghera con alcuni totem e sabato 2 maggio, alle 12:00 saremo in area palco per la presentazione ufficiale. \n\nSarà presente con noi l'illustratore Sebastiano Mandruzzato di A Venessia .",
      "severity": "info",
      "lineAliases": [],
      "affectedStops": [],
      "lastUpdated": "2026-05-01T14:10:16Z",
      "startAt": "2026-05-01T14:10:16Z",
      "endAt": null,
      "source": "actv_telegram",
      "url": null
    },
    {
      "id": "tg-93283e147862",
      "title": "A chi oggi è in servizio, a chi lavora da remoto, a chi ha la fortuna di passare una giornata a casa tra famiglia e amic",
      "description": "A chi oggi è in servizio, a chi lavora da remoto, a chi ha la fortuna di passare una giornata a casa tra famiglia e amici o in uno dei tanti eventi organizzati in città, a chi utilizza i servizi #muoversivenezia per spostarsi per qualsiasi ragione\n\nBuon primo maggio\nBuona festa dei lavoratori\nBuona festa del lavoro\n\nUn abbraccio agli equipaggi, i conducenti, i verificatori, gli addetti vendita, i manutentori, gli operatori dei parcheggi, delle darsene e degli approdi, il personale di terra e di assistenza, lo staff degli eventi, le centrali operative: un abbraccio alla comunità AVM/Actv Venezia e Venezia Unica",
      "severity": "info",
      "lineAliases": [],
      "affectedStops": [],
      "lastUpdated": "2026-05-01T06:03:10Z",
      "startAt": "2026-05-01T06:03:10Z",
      "endAt": null,
      "source": "actv_telegram",
      "url": null
    },
    {
      "id": "tg-48535c340858",
      "title": "test123",
      "description": "test123",
      "severity": "info",
      "lineAliases": [],
      "affectedStops": [],
      "lastUpdated": "2026-04-30T21:44:55Z",
      "startAt": "2026-04-30T21:44:55Z",
      "endAt": null,
      "source": "actv_telegram",
      "url": null
    },
    {
      "id": "tg-463132805d81",
      "title": "⏱ #muoversivenezia | 🚍🚢 Servizi 1 Maggio",
      "description": "⏱ #muoversivenezia | 🚍🚢 Servizi 1 Maggio \n\n📆 venerdì 1 maggio 2026 \n\n➡ Orario festivo per i servizi automobilistico Lido/Pellestrina e di navigazione. People Mover: prima corsa alle ore 08.10, ultima alle 21.50. \n\n🔴 nella news dettagli sulle deviazione dei servizi per il mercato di Mestre e il link per la mercato e manifestazione a Marghera https://actv.avmspa.it/it/content/marghera-1maggio-deviazione-di-mercato \n\nModifiche servizio automobilistico urbano/extraurbano: \n👉 https://actv.avmspa.it/it/content/modifica-ai-servizi-di-trasporto-1-maggio-2026",
      "severity": "warning",
      "lineAliases": [],
      "affectedStops": [],
      "lastUpdated": "2026-04-30T21:32:36Z",
      "startAt": "2026-04-30T21:32:36Z",
      "endAt": null,
      "source": "actv_telegram",
      "url": null
    }
  ]
}